loluukok/__init__.py
loluukok/loluukok.py
loluukok-1.3.dist-info/LICENSE
loluukok-1.3.dist-info/METADATA
loluukok-1.3.dist-info/WHEEL
loluukok-1.3.dist-info/top_level.txt
loluukok-1.3.dist-info/RECORD
