Metadata-Version: 2.1
Name: loluukok
Version: 1.3
Summary: A simple library for file and directory management.
Home-page: https://pypi.org/project/loluukok/1.3
Author: Luuk M. Mastbroek
Author-email: luukm@mastbroek.nl
License: UNKNOWN
Platform: UNKNOWN
Classifier: Programming Language :: Python :: 3
Classifier: License :: OSI Approved :: MIT License
Classifier: Operating System :: OS Independent
Requires-Python: >=3.6
License-File: LICENSE
